kpireport_plot/__init__.py
kpireport_plot/plot.py
kpireport_plot/single_stat.py
kpireport_plot/templates/plot.html
kpireport_plot/templates/plot.md
kpireport_plot/templates/single_stat.html
kpireport_plot/templates/single_stat.md
kpireport_plot/templates/single_stat.slack
kpireport_plot-0.3.1.dist-info/METADATA
kpireport_plot-0.3.1.dist-info/WHEEL
kpireport_plot-0.3.1.dist-info/entry_points.txt
kpireport_plot-0.3.1.dist-info/top_level.txt
kpireport_plot-0.3.1.dist-info/RECORD
