Metadata-Version: 2.1
Name: kpireport-plot
Version: 0.3.1
Summary: UNKNOWN
Home-page: https://kpireporter.com
Author: KPI Reporter LLC
Author-email: dev@kpireporter.com
License: Prosperity Public License
Platform: UNKNOWN
Requires-Dist: kpireport
Requires-Dist: matplotlib
